{
  "positions": [
    {
      "ticket": 1000000,
      "symbol": "EURUSD",
      "type": "BUY",
      "volume": 0.1,
      "open_price": 1.15484,
      "current_price": 1.15817,
      "sl": 0,
      "tp": 0,
      "profit": 33.299999999998334,
      "open_time": "2025-11-10T07:29:07.601815",
      "comment": "SIMULATOR"
    },
    {
      "ticket": 1000001,
      "symbol": "EURUSD",
      "type": "BUY",
      "volume": 0.1,
      "open_price": 1.15475,
      "current_price": 1.15817,
      "sl": 0,
      "tp": 0,
      "profit": 34.19999999999979,
      "open_time": "2025-11-10T07:29:59.765929",
      "comment": "SIMULATOR"
    },
    {
      "ticket": 1000002,
      "symbol": "EURUSD",
      "type": "BUY",
      "volume": 0.1,
      "open_price": 1.15496,
      "current_price": 1.15817,
      "sl": 0,
      "tp": 0,
      "profit": 32.099999999999355,
      "open_time": "2025-11-10T07:33:18.957856",
      "comment": "SIMULATOR"
    }
  ],
  "closed_positions": [],
  "next_ticket": 1000003,
  "initial_balance": 10000,
  "last_updated": "2025-11-10T16:36:53.318530"
}